Bono2FdoJar/__init__.py
Bono2FdoJar/clase_Bono2.py
Bono2FdoJar-0.1.0.dist-info/METADATA
Bono2FdoJar-0.1.0.dist-info/WHEEL
Bono2FdoJar-0.1.0.dist-info/top_level.txt
Bono2FdoJar-0.1.0.dist-info/RECORD
